kenghwee/__init__.py
kenghwee/cs1010s.py
kenghwee/mission04.py
kenghwee/rmrf.py
kenghwee-1.1.dist-info/LICENSE
kenghwee-1.1.dist-info/METADATA
kenghwee-1.1.dist-info/WHEEL
kenghwee-1.1.dist-info/top_level.txt
kenghwee-1.1.dist-info/RECORD
