Metadata-Version: 2.1
Name: kenghwee
Version: 1.1
Summary: A package where a meme becomes a reality.
Home-page: https://github.com/RussellDash332/kenghwee
Download-URL: https://pypi.org/project/kenghwee/
Author: Russell Saerang
Author-email: russellsaerang@gmail.com
License: MIT
Keywords: Kenghwee,Keng Hwee
License-File: LICENSE
Requires-Dist: seaborn
Requires-Dist: cocos2d
Requires-Dist: clrprint
